seqvec/__init__.py
seqvec/seqvec.py
seqvec-0.4.1.dist-info/entry_points.txt
seqvec-0.4.1.dist-info/LICENSE
seqvec-0.4.1.dist-info/WHEEL
seqvec-0.4.1.dist-info/METADATA
seqvec-0.4.1.dist-info/RECORD
