Metadata-Version: 2.1
Name: seqvec
Version: 0.4.1
Summary: Embeeder tool for 'Modelling the Language of Life - Deep Learning Protein Sequences'
Home-page: https://github.com/Rostlab/SeqVec
License: MIT
Author: Michael Heinzinger
Author-email: mheinzinger@rostlab.org
Requires-Python: >=3.6.1
Classifier: Intended Audience :: Science/Research
Classifier: License :: OSI Approved :: MIT License
Classifier: Programming Language :: Python :: 3
Classifier: Programming Language :: Python :: 3.7
Classifier: Programming Language :: Python :: 3.8
Classifier: Topic :: Scientific/Engineering :: Artificial Intelligence
Classifier: Topic :: Scientific/Engineering :: Bio-Informatics
Requires-Dist: allennlp (>=0.9.0,<0.10.0)
Requires-Dist: gevent (==1.4.0)
Requires-Dist: h5py (>=2.10.0,<3.0.0)
Requires-Dist: numpy (>=1.17,<2.0)
Requires-Dist: torch (>=1.2,<2.0)
Requires-Dist: tqdm (>=4.36,<5.0)
Project-URL: Repository, https://github.com/Rostlab/SeqVec
